{"metadata":{},"options":{"plugins":[{"key":"base$1$0","visitor":{"_exploded":{},"_verified":{},"JSXNamespacedName":{"enter":[null]},"JSXElement":{"exit":[null]},"JSXFragment":{"exit":[null]},"Program":{"enter":[null],"exit":[null]},"JSXAttribute":{"enter":[null]}},"options":{"pragma":"React.createElement","pragmaFrag":"React.Fragment","throwIfNamespace":true,"useBuiltIns":false}},{"key":"base$1$1","visitor":{"_exploded":true,"_verified":true},"options":{}},{"key":"base$1$2","visitor":{"ExportDefaultDeclaration":{"enter":[null]},"CallExpression":{"enter":[null]},"_exploded":true,"_verified":true},"options":{}},{"key":"base$0$0","visitor":{"Program":{"enter":[null]},"_exploded":true,"_verified":true},"options":{"generateLetDeclarations":true,"enforceStrictMode":false}},{"key":"base$0$1","visitor":{"_exploded":true,"_verified":true},"options":{}},{"key":"base$0$2","visitor":{"_exploded":{},"_verified":{},"Program":{"enter":[null]},"ImportDeclaration":{"enter":[null,null]},"ClassProperty":{"enter":[null]},"AssignmentPattern":{"enter":[null]},"TypeCastExpression":{"enter":[null,null]},"ImportSpecifier":{"enter":[null]},"ClassDeclaration":{"enter":[null]},"ClassExpression":{"enter":[null]},"FunctionDeclaration":{"enter":[null]},"FunctionExpression":{"enter":[null]},"ObjectMethod":{"enter":[null]},"ArrowFunctionExpression":{"enter":[null]},"ClassMethod":{"enter":[null]},"AnyTypeAnnotation":{"enter":[null]},"ArrayTypeAnnotation":{"enter":[null]},"BooleanTypeAnnotation":{"enter":[null]},"BooleanLiteralTypeAnnotation":{"enter":[null]},"NullLiteralTypeAnnotation":{"enter":[null]},"ClassImplements":{"enter":[null]},"DeclareClass":{"enter":[null]},"DeclareFunction":{"enter":[null]},"DeclareInterface":{"enter":[null]},"DeclareModule":{"enter":[null]},"DeclareModuleExports":{"enter":[null]},"DeclareTypeAlias":{"enter":[null]},"DeclareOpaqueType":{"enter":[null]},"DeclareVariable":{"enter":[null]},"DeclareExportDeclaration":{"enter":[null]},"DeclareExportAllDeclaration":{"enter":[null]},"DeclaredPredicate":{"enter":[null]},"ExistsTypeAnnotation":{"enter":[null]},"FunctionTypeAnnotation":{"enter":[null]},"FunctionTypeParam":{"enter":[null]},"GenericTypeAnnotation":{"enter":[null]},"InferredPredicate":{"enter":[null]},"InterfaceExtends":{"enter":[null]},"InterfaceDeclaration":{"enter":[null]},"IntersectionTypeAnnotation":{"enter":[null]},"MixedTypeAnnotation":{"enter":[null]},"EmptyTypeAnnotation":{"enter":[null]},"NullableTypeAnnotation":{"enter":[null]},"NumberLiteralTypeAnnotation":{"enter":[null]},"NumberTypeAnnotation":{"enter":[null]},"ObjectTypeAnnotation":{"enter":[null]},"ObjectTypeCallProperty":{"enter":[null]},"ObjectTypeIndexer":{"enter":[null]},"ObjectTypeProperty":{"enter":[null]},"ObjectTypeSpreadProperty":{"enter":[null]},"OpaqueType":{"enter":[null]},"QualifiedTypeIdentifier":{"enter":[null]},"StringLiteralTypeAnnotation":{"enter":[null]},"StringTypeAnnotation":{"enter":[null]},"ThisTypeAnnotation":{"enter":[null]},"TupleTypeAnnotation":{"enter":[null]},"TypeofTypeAnnotation":{"enter":[null]},"TypeAlias":{"enter":[null]},"TypeAnnotation":{"enter":[null]},"TypeParameter":{"enter":[null]},"TypeParameterDeclaration":{"enter":[null]},"TypeParameterInstantiation":{"enter":[null]},"UnionTypeAnnotation":{"enter":[null]},"Variance":{"enter":[null]},"VoidTypeAnnotation":{"enter":[null]},"ExportAllDeclaration":{"enter":[null]},"ExportDefaultDeclaration":{"enter":[null]},"ExportNamedDeclaration":{"enter":[null]}},"options":{}},{"key":"base$0$3","visitor":{"CallExpression":{"enter":[null]},"BinaryExpression":{"enter":[null]},"MemberExpression":{"enter":[null],"exit":[null]},"_exploded":true,"_verified":true,"Identifier":{"enter":[null]},"JSXIdentifier":{"enter":[null]}},"options":{"polyfill":false,"useBuiltIns":true}},{"key":"base$0$4","visitor":{"_exploded":true,"_verified":true},"options":{}},{"key":"base$0$5","visitor":{"_exploded":{},"_verified":{},"VariableDeclarator":{"enter":[null]},"ExportNamedDeclaration":{"enter":[null]},"CatchClause":{"enter":[null]},"AssignmentExpression":{"enter":[null]},"ObjectExpression":{"enter":[null]},"FunctionDeclaration":{"enter":[null]},"FunctionExpression":{"enter":[null]},"ObjectMethod":{"enter":[null]},"ArrowFunctionExpression":{"enter":[null]},"ClassMethod":{"enter":[null]},"ForInStatement":{"enter":[null]},"ForOfStatement":{"enter":[null]}},"options":{}},{"key":"transform-meteor-async-await","visitor":{"AwaitExpression":{"enter":[null]},"_exploded":true,"_verified":true,"FunctionDeclaration":{"exit":[null]},"FunctionExpression":{"exit":[null]},"ObjectMethod":{"exit":[null]},"ArrowFunctionExpression":{"exit":[null]},"ClassMethod":{"exit":[null]}},"options":{"useNativeAsyncAwait":false}},{"key":"transform-meteor-dynamic-import","visitor":{"_exploded":{},"_verified":{},"CallExpression":{"enter":[null]}},"options":{}},{"key":"base$0$8","visitor":{"_exploded":{},"_verified":{},"Program":{"enter":[null]}},"options":{}},{"key":"base$0$9","visitor":{"Program":{"exit":[null]},"_exploded":true,"_verified":true},"options":{"allowTopLevelThis":true,"strictMode":false,"loose":true}},{"key":"base$0$10","visitor":{"_exploded":{},"_verified":{},"ClassDeclaration":{"enter":[null]},"ClassExpression":{"enter":[null]}},"options":{"loose":true}}],"compact":false,"ast":true,"babelrc":false,"sourceFileName":"imports/startup/server/fixtures.js","filename":"imports/startup/server/fixtures.js","sourceMaps":true,"envName":"development","cwd":"/Users/tonjelindmark/Documents/teknik_for_sociala_medier/aloha/Aloha","passPerPreset":false,"presets":[],"parserOpts":{"sourceType":"module","sourceFileName":"imports/startup/server/fixtures.js","plugins":["jsx","jsx","flow","flow","objectRestSpread","objectRestSpread","dynamicImport","asyncGenerators","classProperties"]},"generatorOpts":{"filename":"imports/startup/server/fixtures.js","comments":true,"compact":false,"sourceMaps":true,"sourceFileName":"imports/startup/server/fixtures.js"}},"code":"let Meteor;\nmodule.watch(require(\"meteor/meteor\"), {\n  Meteor(v) {\n    Meteor = v;\n  }\n\n}, 0);\nlet Links;\nmodule.watch(require(\"../../api/links/links.js\"), {\n  Links(v) {\n    Links = v;\n  }\n\n}, 1);\nMeteor.startup(() => {\n  // if the Links collection is empty\n  if (Links.find().count() === 0) {\n    const data = [{\n      title: 'Do the Tutorial',\n      url: 'https://www.meteor.com/try',\n      createdAt: new Date()\n    }, {\n      title: 'Follow the Guide',\n      url: 'http://guide.meteor.com',\n      createdAt: new Date()\n    }, {\n      title: 'Read the Docs',\n      url: 'https://docs.meteor.com',\n      createdAt: new Date()\n    }, {\n      title: 'Discussions',\n      url: 'https://forums.meteor.com',\n      createdAt: new Date()\n    }];\n    data.forEach(link => Links.insert(link));\n  }\n});","map":{"version":3,"sources":["imports/startup/server/fixtures.js"],"names":["Meteor","module","watch","require","v","Links","startup","find","count","data","title","url","createdAt","Date","forEach","link","insert"],"mappings":"AAAA,IAAIA,MAAJ;AAAWC,OAAOC,KAAP,CAAaC,QAAQ,eAAR,CAAb,EAAsC;AAACH,SAAOI,CAAP,EAAS;AAACJ,aAAOI,CAAP;AAAS;;AAApB,CAAtC,EAA4D,CAA5D;AAA+D,IAAIC,KAAJ;AAAUJ,OAAOC,KAAP,CAAaC,QAAQ,0BAAR,CAAb,EAAiD;AAACE,QAAMD,CAAN,EAAQ;AAACC,YAAMD,CAAN;AAAQ;;AAAlB,CAAjD,EAAqE,CAArE;AAKpFJ,OAAOM,OAAP,CAAe,MAAM;AACnB;AACA,MAAID,MAAME,IAAN,GAAaC,KAAb,OAAyB,CAA7B,EAAgC;AAC9B,UAAMC,OAAO,CACX;AACEC,aAAO,iBADT;AAEEC,WAAK,4BAFP;AAGEC,iBAAW,IAAIC,IAAJ;AAHb,KADW,EAMX;AACEH,aAAO,kBADT;AAEEC,WAAK,yBAFP;AAGEC,iBAAW,IAAIC,IAAJ;AAHb,KANW,EAWX;AACEH,aAAO,eADT;AAEEC,WAAK,yBAFP;AAGEC,iBAAW,IAAIC,IAAJ;AAHb,KAXW,EAgBX;AACEH,aAAO,aADT;AAEEC,WAAK,2BAFP;AAGEC,iBAAW,IAAIC,IAAJ;AAHb,KAhBW,CAAb;AAuBAJ,SAAKK,OAAL,CAAaC,QAAQV,MAAMW,MAAN,CAAaD,IAAb,CAArB;AACD;AACF,CA5BD","sourcesContent":["// Fill the DB with example data on startup\n\nimport { Meteor } from 'meteor/meteor';\nimport { Links } from '../../api/links/links.js';\n\nMeteor.startup(() => {\n  // if the Links collection is empty\n  if (Links.find().count() === 0) {\n    const data = [\n      {\n        title: 'Do the Tutorial',\n        url: 'https://www.meteor.com/try',\n        createdAt: new Date(),\n      },\n      {\n        title: 'Follow the Guide',\n        url: 'http://guide.meteor.com',\n        createdAt: new Date(),\n      },\n      {\n        title: 'Read the Docs',\n        url: 'https://docs.meteor.com',\n        createdAt: new Date(),\n      },\n      {\n        title: 'Discussions',\n        url: 'https://forums.meteor.com',\n        createdAt: new Date(),\n      },\n    ];\n\n    data.forEach(link => Links.insert(link));\n  }\n});\n"]},"sourceType":"script","hash":"153a6e193bcc0a9b859aa43183f320d7e8ef8a66"}
